{
    "_type": "ogm-quote-summary",
    "productLine": "stone",
    "quoteNumber": "1779095680260",
    "invoiceNumber": "",
    "invoiceDate": "",
    "convertedAt": "",
    "depositReceiptNumber": "",
    "depositRecordedAt": "",
    "depositAmount": null,
    "jobCode": "T1.Inv.Instal",
    "jobType": "Installed",
    "installDate": "",
    "hrsEst": 0,
    "hrsAct": 0,
    "jtNotes": "",
    "cosTotal": 0,
    "cosTax": 0,
    "cosLabor": 0,
    "taxMode": "cos",
    "taxBackoutAmount": 0,
    "taxBase": 0,
    "taxExemptReason": "",
    "useNcRpSplit": true,
    "name": "C C & F Custom Cabinets",
    "phone": "910-424-7475",
    "email": "cfcabinets@nc.rr.com",
    "addr": "Steve Ford",
    "city": "Colin Ford  cfcabinets5@nc.rr.com",
    "installAddr": "",
    "installCity": "",
    "job": "Crown.Expo#1",
    "salesperson": "G Sedberry Olive (SO)",
    "stone": "Sparkling White",
    "sqft": 106.37847222222223,
    "totalSF": 106.37847222222223,
    "date": "May 18, 2026",
    "total": 9210.263333333334,
    "grand": 9210.263333333334,
    "invoiceTotal": null,
    "workflowPhase": "Quoted",
    "status": "quoted",
    "savedAt": "2026-05-18T11:34:54.027Z",
    "linkedCustomerId": "C19E2C155934H13"
}