{
    "id": "C19E2C156D7F8Y6",
    "firstName": "",
    "lastName": "D & J Motors",
    "phone": "323-1317",
    "phone2": "",
    "email": "",
    "email2": "",
    "svcStreet": "249-B West Mountain Drive",
    "svcCity": "Fayetteville, N.C. 28306",
    "sameAddr": false,
    "billStreet": "P.O. Box 65047",
    "billCity": "Fayetteville, N.C. 28306",
    "jobName": "",
    "status": "prospect",
    "rep": "Tanya Wadkins (TW)",
    "source": "QuickBooks",
    "referral": "",
    "notes": "",
    "createdAt": "May 15, 2026",
    "updatedAt": "May 15, 2026",
    "quotes": [],
    "notesLog": []
}
