{
    "id": "C19E2C155C1ED7T",
    "firstName": "",
    "lastName": "Carolina Cabinets",
    "phone": "843-456-8656 Kaitlyn  6/2022",
    "phone2": "",
    "email": "",
    "email2": "",
    "svcStreet": "3290 Pineville School Rd.",
    "svcCity": "Bennettsbilee, NC  29512",
    "sameAddr": true,
    "billStreet": "3290 Pineville School Rd.",
    "billCity": "Bennettsbilee, NC  29512",
    "jobName": "",
    "status": "active",
    "rep": "Tanya Wadkins (TW)",
    "source": "QuickBooks",
    "referral": "",
    "notes": "",
    "createdAt": "May 15, 2026",
    "updatedAt": "May 15, 2026",
    "quotes": [],
    "notesLog": []
}
