{
    "id": "C19E2C156547ZKR",
    "firstName": "",
    "lastName": "Cole, Justin",
    "phone": "624-9907",
    "phone2": "",
    "email": "",
    "email2": "",
    "svcStreet": "Cole, Justin",
    "svcCity": "",
    "sameAddr": true,
    "billStreet": "Cole, Justin",
    "billCity": "",
    "jobName": "",
    "status": "prospect",
    "rep": "Tanya Wadkins (TW)",
    "source": "QuickBooks",
    "referral": "",
    "notes": "",
    "createdAt": "May 15, 2026",
    "updatedAt": "May 15, 2026",
    "quotes": [],
    "notesLog": []
}
