{
    "id": "C19E2C154E3CQK9",
    "firstName": "",
    "lastName": "Banbrick, Steven J.",
    "phone": "240-688-9912",
    "phone2": "",
    "email": "",
    "email2": "",
    "svcStreet": "Myrtle Beach, SC  29572",
    "svcCity": "",
    "sameAddr": true,
    "billStreet": "Myrtle Beach, SC  29572",
    "billCity": "",
    "jobName": "",
    "status": "prospect",
    "rep": "Tanya Wadkins (TW)",
    "source": "QuickBooks",
    "referral": "",
    "notes": "",
    "createdAt": "May 15, 2026",
    "updatedAt": "May 15, 2026",
    "quotes": [],
    "notesLog": []
}
