{
    "id": "C19E2C1554849K5",
    "firstName": "",
    "lastName": "Briscoe, Chuck",
    "phone": "910-868-0725",
    "phone2": "",
    "email": "",
    "email2": "",
    "svcStreet": "222 DeVane Street",
    "svcCity": "Fayetteville, NC  28305",
    "sameAddr": true,
    "billStreet": "222 DeVane Street",
    "billCity": "Fayetteville, NC  28305",
    "jobName": "",
    "status": "active",
    "rep": "Tanya Wadkins (TW)",
    "source": "QuickBooks",
    "referral": "",
    "notes": "",
    "createdAt": "May 15, 2026",
    "updatedAt": "May 15, 2026",
    "quotes": [],
    "notesLog": []
}
