{
    "id": "CMP72X2S34WD",
    "firstName": "",
    "lastName": "Adcox, Ray and Susan",
    "phone": "910-876-4977",
    "phone2": "",
    "email": "",
    "email2": "",
    "svcStreet": "",
    "svcCity": "",
    "sameAddr": false,
    "billStreet": "3500 Godwin Circle",
    "billCity": "Fayetteville, NC",
    "jobName": "",
    "status": "prospect",
    "rep": "Tanya Wadkins (TW)",
    "source": "QuickBooks",
    "referral": "",
    "notes": "",
    "createdAt": "May 15, 2026",
    "updatedAt": "May 15, 2026",
    "quotes": [],
    "notesLog": []
}