{
    "id": "CMP72XQCT6H3",
    "firstName": "",
    "lastName": "Barnes, Atoro & Nieasha",
    "phone": "703-789-5855",
    "phone2": "",
    "email": "",
    "email2": "",
    "svcStreet": "",
    "svcCity": "",
    "sameAddr": false,
    "billStreet": "113 Tellmont Street",
    "billCity": "Raeford, NC  28376",
    "jobName": "",
    "status": "prospect",
    "rep": "Tanya Wadkins (TW)",
    "source": "QuickBooks",
    "referral": "",
    "notes": "",
    "createdAt": "May 15, 2026",
    "updatedAt": "May 15, 2026",
    "quotes": [],
    "notesLog": []
}