{
    "id": "CMP72YIMORMA",
    "firstName": "",
    "lastName": "Brooks, John",
    "phone": "910-308-4986",
    "phone2": "",
    "email": "",
    "email2": "",
    "svcStreet": "",
    "svcCity": "",
    "sameAddr": false,
    "billStreet": "JDB Home Improvements",
    "billCity": "6411 Rannock Drive",
    "jobName": "",
    "status": "prospect",
    "rep": "Tanya Wadkins (TW)",
    "source": "QuickBooks",
    "referral": "",
    "notes": "",
    "createdAt": "May 15, 2026",
    "updatedAt": "May 15, 2026",
    "quotes": [],
    "notesLog": []
}