{
    "id": "CMP72XQ4J1TI",
    "firstName": "",
    "lastName": "Barkman, Japtheth",
    "phone": "910-818-9057",
    "phone2": "",
    "email": "",
    "email2": "",
    "svcStreet": "",
    "svcCity": "",
    "sameAddr": false,
    "billStreet": "2721 Bennington Rd.",
    "billCity": "Fayetteville, NC  28303",
    "jobName": "",
    "status": "active",
    "rep": "Tanya Wadkins (TW)",
    "source": "QuickBooks",
    "referral": "",
    "notes": "",
    "createdAt": "May 15, 2026",
    "updatedAt": "May 15, 2026",
    "quotes": [],
    "notesLog": []
}